quipt_cli/__init__.py
quipt_cli/__main__.py
quipt_cli/parser.py
quipt_cli/serialisation.py
quipt_cli/server_sync.py
quipt_cli-0.1.5.dist-info/LICENSE
quipt_cli-0.1.5.dist-info/METADATA
quipt_cli-0.1.5.dist-info/WHEEL
quipt_cli-0.1.5.dist-info/entry_points.txt
quipt_cli-0.1.5.dist-info/top_level.txt
quipt_cli-0.1.5.dist-info/RECORD
